LICENSE
MANIFEST.in
README.rst
setup.py
voicecoding/__init__.py
voicecoding/__main__.py
voicecoding/code_class.py
voicecoding/data_types.py
voicecoding/eval_command.py
voicecoding/exec_output.py
voicecoding/instructions.py
voicecoding/listen.py
voicecoding.egg-info/PKG-INFO
voicecoding.egg-info/SOURCES.txt
voicecoding.egg-info/dependency_links.txt
voicecoding.egg-info/entry_points.txt
voicecoding.egg-info/requires.txt
voicecoding.egg-info/top_level.txt
voicecoding/commandfunctions/__init__.py
voicecoding/commandfunctions/assign_variable.py
voicecoding/commandfunctions/call_func_method.py
voicecoding/commandfunctions/def_func.py
voicecoding/commandfunctions/for_loop.py
voicecoding/commandfunctions/if_else.py
voicecoding/commandfunctions/import_module.py
voicecoding/commandfunctions/print_data.py
voicecoding/commandfunctions/return_func.py
voicecoding/commandfunctions/while_loop.py
voicecoding/helpers/__init__.py
voicecoding/helpers/format_var_func_name.py
voicecoding/helpers/get_terminal_size.py
voicecoding/helpers/text2num.py
voicecoding/helpers/to_builtin.py
voicecoding/helpers/voice_conversion.py